{
  "id": "009",
  "filename": "009_attached_885c19be02ccf229.png",
  "ok": true,
  "error": null,
  "ms": {
    "extract": 37789,
    "assemble": 20,
    "total": 45565
  },
  "archetype": "x-post",
  "layerCountExtracted": 25,
  "parsePath": "loose",
  "background": "#000000",
  "cutoutCandidates": 1,
  "layersApplied": 4,
  "leavesInResult": 26,
  "verify": {
    "ready": false
  },
  "pixelError": null,
  "textPileOverlaps": 0,
  "pixelScoreRaw": 89.9,
  "pixelScore": 89.9,
  "sideBySide": "/Users/michael/Downloads/NEUEGEN/studio/scratchpad-work/copy-harness/009/side-by-side.png"
}